README.rst
setup.py
bigpy/__init__.py
bigpy/dotdict.py
bigpy/jsonutil.py
bigpy/logutil.py
bigpy/strutil.py
bigpy.egg-info/PKG-INFO
bigpy.egg-info/SOURCES.txt
bigpy.egg-info/dependency_links.txt
bigpy.egg-info/requires.txt
bigpy.egg-info/top_level.txt