Metadata-Version: 1.1
Name: bigpy
Version: 0.2.0
Summary: A collection of various Python utilities
Home-page: https://bitbucket.org/pgolec/bigpy
Author: Patrick Golec
Author-email: pgolec+pypi@gmail.com
License: BSD
Keywords: utilities
Platform: UNKNOWN
Classifier: Development Status :: 3 - Alpha
Classifier: Intended Audience :: Developers
Classifier: License :: OSI Approved :: BSD License
Classifier: Programming Language :: Python :: 2
Classifier: Programming Language :: Python :: 3
